aurite/__init__.py
aurite/aurite.py
aurite/bin/__init__.py
aurite/bin/api/__init__.py
aurite/bin/api/api.py
aurite/bin/api/routes/__init__.py
aurite/bin/api/routes/config_routes.py
aurite/bin/api/routes/execution_routes.py
aurite/bin/api/routes/system_routes.py
aurite/bin/api/routes/tools_routes.py
aurite/bin/cli/__init__.py
aurite/bin/cli/cli.py
aurite/bin/cli/commands/__init__.py
aurite/bin/cli/commands/init.py
aurite/bin/cli/commands/list.py
aurite/bin/cli/commands/run.py
aurite/bin/cli/commands/show.py
aurite/bin/cli/main.py
aurite/bin/dependencies.py
aurite/bin/studio/__init__.py
aurite/bin/studio/static/.htaccess
aurite/bin/studio/static/README.md
aurite/bin/studio/static/apple-touch-icon.png
aurite/bin/studio/static/asset-manifest.json
aurite/bin/studio/static/browserconfig.xml
aurite/bin/studio/static/favicon.ico
aurite/bin/studio/static/index.html
aurite/bin/studio/static/logo.png
aurite/bin/studio/static/manifest.json
aurite/bin/studio/static/robots.txt
aurite/bin/studio/static/sitemap.xml
aurite/bin/studio/static/static/css/main.96344725.css
aurite/bin/studio/static/static/css/main.96344725.css.map
aurite/bin/studio/static/static/js/400.275c405c.chunk.js
aurite/bin/studio/static/static/js/400.275c405c.chunk.js.map
aurite/bin/studio/static/static/js/main.e1e008df.js
aurite/bin/studio/static/static/js/main.e1e008df.js.LICENSE.txt
aurite/bin/studio/static/static/js/main.e1e008df.js.map
aurite/bin/studio/static_server.py
aurite/bin/studio/studio.py
aurite/bin/studio/utils.py
aurite/bin/tui/__init__.py
aurite/bin/tui/apps/__init__.py
aurite/bin/tui/apps/chat.py
aurite/bin/tui/apps/edit.py
aurite/bin/tui/styles/chat.tcss
aurite/bin/tui/styles/edit.tcss
aurite/bin/tui/styles/main.tcss
aurite/bin/tui/tui.py
aurite/execution/__init__.py
aurite/execution/aurite_engine.py
aurite/execution/mcp_host/__init__.py
aurite/execution/mcp_host/filtering.py
aurite/execution/mcp_host/foundation/__init__.py
aurite/execution/mcp_host/foundation/roots.py
aurite-0.3.28.dist-info/LICENSE
aurite-0.3.28.dist-info/METADATA
aurite-0.3.28.dist-info/WHEEL
aurite-0.3.28.dist-info/entry_points.txt
aurite-0.3.28.dist-info/RECORD
