Metadata-Version: 2.3
Name: aurite
Version: 0.3.28
Summary: Aurite Agents is an agent development and runtime framework.
License: MIT License
Keywords: ai,agent,mcp,framework,llm,anthropic
Author: Ryan W
Author-email: ryan@aurite.ai
Requires-Python: >=3.11,<4.0.0
Classifier: Development Status :: 3 - Alpha
Classifier: Intended Audience :: Developers
Classifier: License :: OSI Approved :: MIT License
Classifier: Programming Language :: Python :: 3
Classifier: Programming Language :: Python :: 3.11
Classifier: Topic :: Scientific/Engineering :: Artificial Intelligence
Classifier: Topic :: Software Development :: Libraries :: Application Frameworks
Requires-Dist: anyio (>=4.9.0,<5.0.0)
Requires-Dist: colorlog (>=6.9.0,<7.0.0)
Requires-Dist: cryptography (>=43.0.0,<46.0.0)
Requires-Dist: exceptiongroup (>=1.3.0,<2.0.0)
Requires-Dist: fastapi (>=0.115.14,<0.116.0)
Requires-Dist: fastmcp (>=2.11.3,<3.0.0)
Requires-Dist: jsonschema (>=4.24.0,<5.0.0)
Requires-Dist: langfuse (>=2,<3)
Requires-Dist: litellm (>=1.75.4,<2.0.0)
Requires-Dist: mcp (>=1.10.1,<2.0.0)
Requires-Dist: openai (>=1.99.6,<1.100.0)
Requires-Dist: pydantic (>=2.11.7,<3.0.0)
Requires-Dist: pydantic-settings (>=2.10.1,<3.0.0)
Requires-Dist: pydub (>=0.25.1,<0.26.0)
Requires-Dist: python-dotenv (>=1.1.1,<2.0.0)
Requires-Dist: pytz (>=2025.2,<2026.0)
Requires-Dist: pyyaml (>=6.0.2,<7.0.0)
Requires-Dist: sqlalchemy (>=2.0.41,<3.0.0)
Requires-Dist: termcolor (>=3.1.0,<4.0.0)
Requires-Dist: textual[syntax] (>=3.5.0,<4.0.0)
Requires-Dist: toml (>=0.10.2,<0.11.0)
Requires-Dist: tomli (>=2.2.1,<3.0.0)
Requires-Dist: typer[all] (>=0.16.0,<0.17.0)
Requires-Dist: uvicorn (>=0.29.0,<0.36.0)
Project-URL: Homepage, https://publish.obsidian.md/aurite/HOME
Project-URL: Repository, https://github.com/Aurite-ai/aurite-agents
